.gitlab-ci.yml
AUTHORS
ChangeLog
README.md
requirements.txt
setup.cfg
setup.py
doc/Makefile
doc/make.bat
doc/source/conf.py
doc/source/index.rst
py_figure_eight.egg-info/PKG-INFO
py_figure_eight.egg-info/SOURCES.txt
py_figure_eight.egg-info/dependency_links.txt
py_figure_eight.egg-info/not-zip-safe
py_figure_eight.egg-info/pbr.json
py_figure_eight.egg-info/requires.txt
py_figure_eight.egg-info/top_level.txt
src/figure_eight/__init__.py
src/figure_eight/exceptions.py
src/figure_eight/figure_eight.py