Metadata-Version: 1.0
Name: py-figure-eight
Version: 0.3.5
Summary: Figure Eight APIs in a Python Friendly Form
Home-page: https://gitlab.com/mgreenberg/py-figure-eight
Author: Matthew Greenberg
Author-email: mgreenberg@gumgum.com
License: UNKNOWN
Platform: UNKNOWN
